SmartSpider/__init__.py
SmartSpider/models.py
SmartSpider/crawler/__init__.py
SmartSpider/crawler/crawler.py
SmartSpider/crawler/core/__init__.py
SmartSpider/crawler/core/change_detector.py
SmartSpider/crawler/core/fetcher.py
SmartSpider/crawler/core/queue.py
SmartSpider/crawler/core/scheduler.py
SmartSpider/crawler/core/scope.py
SmartSpider/scraper/__init__.py
SmartSpider/scraper/scraper.py
SmartSpider/scraper/core/__init__.py
SmartSpider/scraper/core/scrape_fns.py
smartspider-0.0.3.dist-info/METADATA
smartspider-0.0.3.dist-info/WHEEL
smartspider-0.0.3.dist-info/licenses/LICENSE
smartspider-0.0.3.dist-info/RECORD
