Metadata-Version: 2.4
Name: SmartSpider
Version: 0.0.3
Summary: A modular adaptive web crawler framework with incremental, continuous, and scope-limited crawling support.
Project-URL: Homepage, https://github.com/danez13/SmartSpider
Project-URL: Issues, https://github.com/danez13/SmartSpider/issues
Author-email: Daniel <hernandezdaniel1702@gmail.com>
License-Expression: MIT
License-File: LICENSE
Classifier: Operating System :: OS Independent
Classifier: Programming Language :: Python :: 3
Requires-Python: >=3.7
Requires-Dist: anthropic
Requires-Dist: beautifulsoup4
Requires-Dist: openai
Requires-Dist: pytest
Requires-Dist: requests
